[
  {
    "model_version": 1,
    "70%": 8.08,
    "80%": 8.47,
    "20%": 6.68,
    "10%": 6.31,
    "30%": 6.93,
    "date": "2021-05-20",
    "40%": 7.21,
    "60%": 7.78,
    "50%": 7.47,
    "90%": 9.01
  },
  {
    "model_version": 1,
    "70%": 7.89,
    "80%": 8.22,
    "20%": 6.63,
    "10%": 6.26,
    "30%": 6.89,
    "date": "2021-06-01",
    "40%": 7.14,
    "60%": 7.6,
    "50%": 7.34,
    "90%": 8.64
  },
  {
    "model_version": 1,
    "70%": 7.96,
    "80%": 8.3,
    "20%": 6.74,
    "10%": 6.26,
    "30%": 6.98,
    "date": "2021-06-15",
    "40%": 7.24,
    "60%": 7.74,
    "50%": 7.48,
    "90%": 8.83
  },
  {
    "model_version": 1,
    "70%": 7.5,
    "80%": 7.77,
    "20%": 6.36,
    "10%": 6.02,
    "30%": 6.58,
    "date": "2021-07-06",
    "40%": 6.83,
    "60%": 7.25,
    "50%": 7.04,
    "90%": 8.15
  },
  {
    "model_version": 1,
    "70%": 7.55,
    "80%": 7.78,
    "20%": 6.5,
    "10%": 6.2,
    "30%": 6.74,
    "date": "2021-07-20",
    "40%": 6.95,
    "60%": 7.31,
    "50%": 7.12,
    "90%": 8.12
  },
  {
    "model_version": 1,
    "70%": 7.61,
    "80%": 7.87,
    "20%": 6.61,
    "10%": 6.33,
    "30%": 6.82,
    "date": "2021-08-03",
    "40%": 7.01,
    "60%": 7.41,
    "50%": 7.2,
    "90%": 8.29
  },
  {
    "model_version": 1,
    "70%": 7.75,
    "80%": 8.02,
    "20%": 6.79,
    "10%": 6.49,
    "30%": 7.02,
    "date": "2021-08-17",
    "40%": 7.2,
    "60%": 7.56,
    "50%": 7.39,
    "90%": 8.34
  },
  {
    "model_version": 1,
    "70%": 8.16,
    "80%": 8.43,
    "20%": 7.22,
    "10%": 6.97,
    "30%": 7.47,
    "date": "2021-09-07",
    "40%": 7.64,
    "60%": 7.96,
    "50%": 7.8,
    "90%": 8.8
  },
  {
    "model_version": 1,
    "70%": 7.98,
    "80%": 8.19,
    "20%": 7.22,
    "10%": 6.98,
    "50%": 7.67,
    "date": "2021-09-21",
    "40%": 7.54,
    "60%": 7.81,
    "30%": 7.37,
    "90%": 8.51
  },
  {
    "model_version": 1,
    "70%": 8.19,
    "80%": 8.36,
    "20%": 7.44,
    "10%": 7.19,
    "30%": 7.61,
    "date": "2021-10-05",
    "40%": 7.74,
    "60%": 8.03,
    "50%": 7.9,
    "90%": 8.61
  },
  {
    "model_version": 1,
    "70%": 8.46,
    "80%": 8.65,
    "20%": 7.73,
    "10%": 7.51,
    "50%": 8.16,
    "date": "2021-10-19",
    "40%": 8.03,
    "60%": 8.33,
    "30%": 7.9,
    "90%": 8.87
  }
]