[{"SMP": 0, "RenCas": 0, "Butter": 0, "QuantitySold": "46418", "Ched": 0, "LAC": 0, "AMF": 0, "TwelveMonthQtySold": "901050", "date": "2014-01-07", "WMP": 0, "MPC70": 0, "trading_event": 107, "BMP": 0}, {"SMP": 184858, "RenCas": 10123, "Butter": 37249, "QuantitySold": "41024", "Ched": 31907, "LAC": 0, "AMF": 90288, "TwelveMonthQtySold": "891483", "date": "2014-01-21", "WMP": 522812, "MPC70": 6374, "trading_event": 108, "BMP": 7485}, {"SMP": 195511, "RenCas": 10598, "Butter": 40782, "QuantitySold": "35399", "Ched": 33363, "LAC": 521, "AMF": 93584, "TwelveMonthQtySold": "940787", "date": "2014-02-04", "WMP": 551697, "MPC70": 6785, "trading_event": 109, "BMP": 7946}, {"SMP": 197172, "RenCas": 10521, "Butter": 44416, "QuantitySold": "34568", "Ched": 32247, "LAC": 0, "AMF": 91179, "TwelveMonthQtySold": "938978", "date": "2014-02-18", "WMP": 548585, "MPC70": 6623, "trading_event": 110, "BMP": 7996}, {"SMP": 197040, "RenCas": 10437, "Butter": 47604, "QuantitySold": "41086", "Ched": 31488, "LAC": 0, "AMF": 88384, "TwelveMonthQtySold": "942587", "date": "2014-03-04", "WMP": 552655, "MPC70": 6466, "trading_event": 111, "BMP": 8124}, {"SMP": 197551, "RenCas": 10239, "Butter": 50736, "QuantitySold": "39008", "Ched": 30684, "LAC": 0, "AMF": 86617, "TwelveMonthQtySold": "937849", "date": "2014-03-18", "WMP": 547304, "MPC70": 6255, "trading_event": 112, "BMP": 8074}, {"SMP": 189048, "RenCas": 9711, "Butter": 50736, "QuantitySold": "39653", "Ched": 28355, "LAC": 389, "AMF": 81496, "TwelveMonthQtySold": "890759", "date": "2014-04-01", "WMP": 517401, "MPC70": 5749, "trading_event": 113, "BMP": 7874}, {"SMP": 190716, "RenCas": 9484, "Butter": 53161, "QuantitySold": "36549", "Ched": 27763, "LAC": 0, "AMF": 80923, "TwelveMonthQtySold": "891925", "date": "2014-04-15", "WMP": 515927, "MPC70": 5352, "trading_event": 114, "BMP": 8093}, {"SMP": 199125, "RenCas": 9431, "Butter": 57905, "QuantitySold": "38174", "Ched": 28405, "LAC": 0, "AMF": 84058, "TwelveMonthQtySold": "927930", "date": "2014-05-06", "WMP": 534776, "MPC70": 0, "trading_event": 115, "BMP": 8493}, {"SMP": 200259, "RenCas": 9116, "Butter": 60211, "QuantitySold": "33677", "Ched": 28018, "LAC": 0, "AMF": 84271, "TwelveMonthQtySold": "924175", "date": "2014-05-20", "WMP": 528456, "MPC70": 0, "trading_event": 116, "BMP": 8493}, {"SMP": 204198, "RenCas": 8778, "Butter": 60712, "QuantitySold": "37012", "Ched": 27513, "LAC": 0, "AMF": 84202, "TwelveMonthQtySold": "931794", "date": "2014-06-03", "WMP": 532896, "MPC70": 0, "trading_event": 117, "BMP": 8442}, {"SMP": 210062, "RenCas": 8525, "Butter": 61983, "QuantitySold": "31984", "Ched": 27398, "LAC": 0, "AMF": 85244, "TwelveMonthQtySold": "948880", "date": "2014-06-17", "WMP": 542372, "MPC70": 0, "trading_event": 118, "BMP": 8392}, {"SMP": 216008, "RenCas": 8306, "Butter": 63013, "QuantitySold": "41513", "Ched": 27448, "LAC": 0, "AMF": 86062, "TwelveMonthQtySold": "972539", "date": "2014-07-01", "WMP": 558306, "MPC70": 0, "trading_event": 119, "BMP": 8221}, {"SMP": 221955, "RenCas": 8427, "Butter": 64788, "QuantitySold": "36656", "Ched": 28170, "LAC": 0, "AMF": 87137, "TwelveMonthQtySold": "995176", "date": "2014-07-15", "WMP": 571118, "MPC70": 0, "trading_event": 120, "BMP": 8231}, {"SMP": 222720, "RenCas": 8301, "Butter": 64943, "QuantitySold": "48380", "Ched": 28100, "LAC": 688, "AMF": 84973, "TwelveMonthQtySold": "1001094", "date": "2014-08-05", "WMP": 578653, "MPC70": 0, "trading_event": 121, "BMP": 8054}, {"SMP": 231050, "RenCas": 8298, "Butter": 66117, "QuantitySold": "46387", "Ched": 28848, "LAC": 0, "SWP": 0, "AMF": 85507, "TwelveMonthQtySold": "1017134", "date": "2014-08-19", "WMP": 584270, "MPC70": 0, "trading_event": 122, "BMP": 7694}, {"SMP": 241061, "RenCas": 8443, "Butter": 68170, "QuantitySold": "57010", "Ched": 29331, "LAC": 0, "SWP": 0, "AMF": 89484, "TwelveMonthQtySold": "1054146", "date": "2014-09-02", "WMP": 604163, "MPC70": 0, "trading_event": 123, "BMP": 8144}, {"SMP": 244627, "RenCas": 8587, "Butter": 68615, "QuantitySold": "50801", "Ched": 29651, "LAC": 0, "SWP": 0, "AMF": 91746, "TwelveMonthQtySold": "1061878", "date": "2014-09-16", "WMP": 605273, "MPC70": 0, "trading_event": 124, "BMP": 8029}, {"SMP": 247879, "RenCas": 8288, "Butter": 69677, "QuantitySold": "55057", "Ched": 30491, "LAC": 0, "SWP": 0, "AMF": 94189, "TwelveMonthQtySold": "1079717", "date": "2014-10-01", "WMP": 615592, "MPC70": 0, "trading_event": 125, "BMP": 8251}, {"SMP": 246722, "RenCas": 8148, "Butter": 69574, "QuantitySold": "50816", "Ched": 30802, "LAC": 0, "SWP": 0, "AMF": 94966, "TwelveMonthQtySold": "1077483", "date": "2014-10-15", "WMP": 613687, "MPC70": 0, "trading_event": 126, "BMP": 8234}, {"SMP": 247199, "RenCas": 8279, "Butter": 69540, "QuantitySold": "45499", "Ched": 31620, "LAC": 0, "SWP": 0, "AMF": 94725, "TwelveMonthQtySold": "1087915", "date": "2014-11-04", "WMP": 622808, "MPC70": 0, "trading_event": 127, "BMP": 8344}, {"SMP": 245243, "RenCas": 8316, "Butter": 69756, "QuantitySold": "39613", "Ched": 32005, "LAC": 0, "SWP": 0, "AMF": 93578, "TwelveMonthQtySold": "1073715", "date": "2014-11-18", "WMP": 611341, "MPC70": 0, "trading_event": 128, "BMP": 8249}, {"SMP": 245968, "RenCas": 8379, "Butter": 69826, "QuantitySold": "39273", "Ched": 32580, "LAC": 0, "SWP": 0, "AMF": 92758, "TwelveMonthQtySold": "1074552", "date": "2014-12-02", "WMP": 611599, "MPC70": 0, "trading_event": 129, "BMP": 8374}, {"SMP": 245811, "RenCas": 8486, "Butter": 69974, "QuantitySold": "35390", "Ched": 32805, "LAC": 0, "SWP": 250, "AMF": 92149, "TwelveMonthQtySold": "1071880", "date": "2014-12-16", "WMP": 609392, "MPC70": 0, "trading_event": 130, "BMP": 8310}, {"SMP": 235972, "RenCas": 8064, "Butter": 67061, "QuantitySold": "33669", "Ched": 31655, "LAC": 0, "SWP": 0, "AMF": 87078, "TwelveMonthQtySold": "1035020", "date": "2015-01-06", "WMP": 592835, "MPC70": 0, "trading_event": 131, "BMP": 8053}, {"SMP": 237169, "RenCas": 8212, "Butter": 66011, "QuantitySold": "31326", "Ched": 32432, "LAC": 0, "SWP": 681, "AMF": 86467, "TwelveMonthQtySold": "1042575", "date": "2015-01-20", "WMP": 600038, "MPC70": 0, "trading_event": 132, "BMP": 8055}, {"SMP": 246039, "RenCas": 8835, "Butter": 68244, "QuantitySold": "28000", "Ched": 34809, "LAC": 0, "SWP": 911, "AMF": 89818, "TwelveMonthQtySold": "1088074", "date": "2015-02-03", "WMP": 627410, "MPC70": 0, "trading_event": 133, "BMP": 8498}, {"SMP": 244102, "RenCas": 8985, "Butter": 66851, "QuantitySold": "22957", "Ched": 35592, "LAC": 0, "SWP": 0, "AMF": 89773, "TwelveMonthQtySold": "1078383", "date": "2015-02-17", "WMP": 620817, "MPC70": 0, "trading_event": 134, "BMP": 8287}, {"SMP": 239716, "RenCas": 9093, "Butter": 65129, "QuantitySold": "22094", "Ched": 36106, "LAC": 0, "SWP": 1261, "AMF": 89198, "TwelveMonthQtySold": "1065359", "date": "2015-03-03", "WMP": 613979, "MPC70": 0, "trading_event": 135, "BMP": 8337}, {"SMP": 237523, "RenCas": 9253, "Butter": 63891, "QuantitySold": "20258", "Ched": 36687, "LAC": 0, "SWP": 0, "AMF": 88777, "TwelveMonthQtySold": "1048805", "date": "2015-03-17", "WMP": 600962, "MPC70": 0, "trading_event": 136, "BMP": 8142}, {"SMP": 228465, "RenCas": 8929, "Butter": 60759, "QuantitySold": "23162", "Ched": 35192, "LAC": 0, "SWP": 0, "AMF": 85457, "TwelveMonthQtySold": "1000947", "date": "2015-04-01", "WMP": 570912, "MPC70": 0, "trading_event": 137, "BMP": 7992}, {"SMP": 225445, "RenCas": 9103, "Butter": 60055, "QuantitySold": "25596", "Ched": 35728, "LAC": 250, "SWP": 0, "AMF": 84480, "TwelveMonthQtySold": "988198", "date": "2015-04-15", "WMP": 562477, "MPC70": 0, "trading_event": 138, "BMP": 7929}, {"SMP": 228609, "RenCas": 9595, "Butter": 60835, "QuantitySold": "27369", "Ched": 38429, "LAC": 250, "SWP": 0, "AMF": 86317, "TwelveMonthQtySold": "1006500", "date": "2015-05-05", "WMP": 571001, "MPC70": 0, "trading_event": 139, "BMP": 8387}, {"SMP": 225285, "RenCas": 9742, "Butter": 60191, "QuantitySold": "26535", "Ched": 39125, "LAC": 150, "SWP": 0, "AMF": 84524, "TwelveMonthQtySold": "994058", "date": "2015-05-19", "WMP": 563880, "MPC70": 0, "trading_event": 140, "BMP": 8249}, {"SMP": 221566, "RenCas": 9785, "Butter": 59263, "QuantitySold": "27711", "Ched": 39337, "LAC": 150, "SWP": 0, "AMF": 82192, "TwelveMonthQtySold": "981584", "date": "2015-06-02", "WMP": 557780, "MPC70": 0, "trading_event": 141, "BMP": 8521}, {"SMP": 215733, "RenCas": 9845, "Butter": 58539, "QuantitySold": "24047", "Ched": 39642, "LAC": 150, "SWP": 0, "AMF": 80610, "TwelveMonthQtySold": "960756", "date": "2015-06-16", "WMP": 544993, "MPC70": 0, "trading_event": 142, "BMP": 8447}, {"SMP": 210332, "RenCas": 9858, "Butter": 57031, "QuantitySold": "33200", "Ched": 39386, "LAC": 150, "SWP": 0, "AMF": 79377, "TwelveMonthQtySold": "944910", "date": "2015-07-01", "WMP": 537437, "MPC70": 0, "trading_event": 143, "BMP": 8732}, {"SMP": 205364, "RenCas": 9883, "Butter": 56111, "QuantitySold": "31691", "Ched": 39376, "LAC": 349, "SWP": 0, "AMF": 78739, "TwelveMonthQtySold": "930853", "date": "2015-07-15", "WMP": 529821, "MPC70": 0, "trading_event": 144, "BMP": 8774}, {"SMP": 202593, "RenCas": 9987, "Butter": 54525, "QuantitySold": "46527", "Ched": 38869, "LAC": 596, "SWP": 0, "AMF": 77955, "TwelveMonthQtySold": "921673", "date": "2015-08-04", "WMP": 525701, "MPC70": 0, "trading_event": 145, "BMP": 9186}, {"SMP": 199548, "RenCas": 10306, "Butter": 53086, "QuantitySold": "36904", "Ched": 38859, "LAC": 891, "SWP": 0, "AMF": 78594, "TwelveMonthQtySold": "910034", "date": "2015-08-18", "WMP": 517461, "MPC70": 0, "trading_event": 146, "BMP": 9028}, {"SMP": 193175, "RenCas": 10580, "Butter": 52978, "QuantitySold": "35865", "Ched": 38476, "LAC": 1185, "SWP": 0, "AMF": 79654, "TwelveMonthQtySold": "904068", "date": "2015-09-01", "WMP": 516497, "MPC70": 0, "trading_event": 147, "BMP": 9262}, {"SMP": 189202, "RenCas": 10798, "Butter": 53401, "QuantitySold": "36050", "Ched": 38343, "LAC": 1481, "SWP": 0, "AMF": 79995, "TwelveMonthQtySold": "891103", "date": "2015-09-15", "WMP": 506560, "MPC70": 0, "trading_event": 148, "BMP": 9062}, {"SMP": 177453, "RenCas": 10889, "Butter": 51471, "QuantitySold": "35243", "Ched": 37838, "LAC": 1770, "SWP": 0, "AMF": 75714, "TwelveMonthQtySold": "850806", "date": "2015-10-06", "WMP": 484698, "MPC70": 0, "trading_event": 149, "BMP": 8712}, {"SMP": 176322, "RenCas": 10982, "Butter": 51565, "QuantitySold": "34519", "Ched": 37863, "LAC": 2070, "SWP": 0, "AMF": 75675, "TwelveMonthQtySold": "845841", "date": "2015-10-20", "WMP": 480403, "MPC70": 0, "trading_event": 150, "BMP": 8700}, {"SMP": 185956, "RenCas": 11353, "Butter": 54645, "QuantitySold": "33997", "Ched": 39315, "LAC": 2318, "SWP": 0, "AMF": 79802, "TwelveMonthQtySold": "892368", "date": "2015-11-03", "WMP": 507613, "MPC70": 0, "trading_event": 151, "BMP": 9105}, {"SMP": 185231, "RenCas": 11188, "Butter": 54863, "QuantitySold": "30044", "Ched": 39047, "LAC": 2554, "SWP": 0, "AMF": 79980, "TwelveMonthQtySold": "880892", "date": "2015-11-17", "WMP": 496708, "MPC70": 0, "trading_event": 152, "BMP": 9060}, {"SMP": 183853, "RenCas": 11167, "Butter": 55115, "QuantitySold": "28158", "Ched": 38815, "LAC": 2854, "SWP": 0, "AMF": 80471, "TwelveMonthQtySold": "870370", "date": "2015-12-01", "WMP": 486790, "MPC70": 0, "trading_event": 153, "BMP": 9044}, {"SMP": 181251, "RenCas": 11074, "Butter": 55652, "QuantitySold": "24888", "Ched": 38513, "LAC": 3140, "SWP": 0, "AMF": 80834, "TwelveMonthQtySold": "849410", "date": "2015-12-15", "WMP": 467641, "MPC70": 0, "trading_event": 154, "BMP": 9044}, {"SMP": 166621, "RenCas": 10368, "Butter": 53727, "QuantitySold": "25671", "Ched": 36008, "LAC": 3440, "SWP": 0, "AMF": 77866, "TwelveMonthQtySold": "778795", "date": "2016-01-05", "WMP": 420207, "MPC70": 0, "trading_event": 155, "BMP": 8673}, {"SMP": 164487, "RenCas": 10287, "Butter": 54090, "QuantitySold": "21930", "Ched": 35417, "LAC": 3740, "SWP": 0, "AMF": 77983, "TwelveMonthQtySold": "762498", "date": "2016-01-19", "WMP": 406249, "MPC70": 0, "trading_event": 156, "BMP": 8665}, {"SMP": 172708, "RenCas": 10850, "Butter": 56445, "QuantitySold": "24474", "Ched": 36808, "LAC": 4040, "SWP": 0, "AMF": 81213, "TwelveMonthQtySold": "796495", "date": "2016-02-02", "WMP": 423911, "MPC70": 0, "trading_event": 157, "BMP": 8940}, {"SMP": 170551, "RenCas": 10865, "Butter": 56147, "QuantitySold": "22021", "Ched": 35696, "LAC": 4332, "SWP": 0, "AMF": 81013, "TwelveMonthQtySold": "781040", "date": "2016-02-16", "WMP": 412189, "MPC70": 0, "trading_event": 158, "BMP": 8897}, {"SMP": 167986, "RenCas": 10881, "Butter": 55549, "QuantitySold": "21880", "Ched": 34754, "LAC": 4632, "SWP": 0, "AMF": 80496, "TwelveMonthQtySold": "769585", "date": "2016-03-01", "WMP": 405143, "MPC70": 0, "trading_event": 159, "BMP": 8894}, {"SMP": 167868, "RenCas": 10944, "Butter": 55182, "QuantitySold": "20406", "Ched": 34015, "LAC": 4932, "SWP": 0, "AMF": 80168, "TwelveMonthQtySold": "755200", "date": "2016-03-15", "WMP": 392172, "MPC70": 0, "trading_event": 160, "BMP": 8919}, {"SMP": 167330, "RenCas": 11274, "Butter": 54688, "QuantitySold": "22682", "Ched": 33173, "LAC": 5230, "SWP": 0, "AMF": 79738, "TwelveMonthQtySold": "745481", "date": "2016-04-05", "WMP": 384293, "MPC70": 0, "trading_event": 161, "BMP": 9005}, {"SMP": 167436, "RenCas": 11500, "Butter": 54418, "QuantitySold": "21206", "Ched": 32202, "LAC": 5530, "SWP": 0, "AMF": 79286, "TwelveMonthQtySold": "733742", "date": "2016-04-19", "WMP": 373800, "MPC70": 0, "trading_event": 162, "BMP": 8820}, {"SMP": 166052, "RenCas": 11815, "Butter": 54083, "QuantitySold": "20615", "Ched": 31142, "LAC": 5822, "SWP": 0, "AMF": 79187, "TwelveMonthQtySold": "726890", "date": "2016-05-03", "WMP": 369386, "MPC70": 0, "trading_event": 163, "BMP": 8903}, {"SMP": 165247, "RenCas": 12271, "Butter": 53920, "QuantitySold": "18113", "Ched": 30157, "LAC": 6122, "SWP": 0, "AMF": 79495, "TwelveMonthQtySold": "720911", "date": "2016-05-17", "WMP": 364717, "MPC70": 0, "trading_event": 164, "BMP": 8732}, {"SMP": 164749, "RenCas": 12431, "Butter": 54107, "QuantitySold": "24046", "Ched": 29205, "LAC": 6408, "SWP": 0, "AMF": 80351, "TwelveMonthQtySold": "719834", "date": "2016-06-01", "WMP": 363546, "MPC70": 0, "trading_event": 165, "BMP": 8787}, {"SMP": 164783, "RenCas": 12675, "Butter": 54510, "QuantitySold": "23089", "Ched": 28603, "LAC": 6690, "SWP": 0, "AMF": 81308, "TwelveMonthQtySold": "718146", "date": "2016-06-15", "WMP": 360903, "MPC70": 0, "trading_event": 166, "BMP": 8674}, {"SMP": 161132, "RenCas": 12481, "Butter": 53276, "QuantitySold": "32500", "Ched": 26753, "LAC": 7190, "SWP": 0, "AMF": 79500, "TwelveMonthQtySold": "697408", "date": "2016-07-05", "WMP": 348684, "MPC70": 0, "trading_event": 167, "BMP": 8392}, {"SMP": 161134, "RenCas": 12478, "Butter": 53307, "QuantitySold": "31348", "Ched": 26328, "LAC": 7385, "SWP": 0, "AMF": 79993, "TwelveMonthQtySold": "693018", "date": "2016-07-19", "WMP": 343956, "MPC70": 0, "trading_event": 168, "BMP": 8437}, {"SMP": 167659, "RenCas": 12713, "Butter": 55282, "QuantitySold": "34928", "Ched": 26593, "LAC": 7885, "SWP": 0, "AMF": 83109, "TwelveMonthQtySold": "713633", "date": "2016-08-02", "WMP": 351406, "MPC70": 0, "trading_event": 169, "BMP": 8986}, {"SMP": 166836, "RenCas": 12562, "Butter": 55358, "QuantitySold": "37766", "Ched": 26228, "LAC": 8138, "SWP": 0, "AMF": 83483, "TwelveMonthQtySold": "704377", "date": "2016-08-16", "WMP": 343083, "MPC70": 0, "trading_event": 170, "BMP": 8689}, {"SMP": 159587, "RenCas": 11893, "Butter": 53591, "QuantitySold": "36748", "Ched": 25679, "LAC": 8049, "SWP": 0, "AMF": 79675, "TwelveMonthQtySold": "674177", "date": "2016-09-06", "WMP": 327300, "MPC70": 0, "trading_event": 171, "BMP": 8403}, {"SMP": 159676, "RenCas": 11653, "Butter": 53552, "QuantitySold": "35086", "Ched": 25869, "LAC": 8234, "SWP": 0, "AMF": 78341, "TwelveMonthQtySold": "673219", "date": "2016-09-20", "WMP": 327395, "MPC70": 0, "trading_event": 172, "BMP": 8499}, {"SMP": 159891, "RenCas": 11576, "Butter": 53711, "QuantitySold": "33937", "Ched": 25654, "LAC": 8445, "SWP": 0, "AMF": 77658, "TwelveMonthQtySold": "672519", "date": "2016-10-04", "WMP": 326959, "MPC70": 0, "trading_event": 173, "BMP": 8625}, {"SMP": 159898, "RenCas": 11514, "Butter": 53369, "QuantitySold": "31525", "Ched": 25498, "LAC": 8627, "SWP": 0, "AMF": 77794, "TwelveMonthQtySold": "672176", "date": "2016-10-18", "WMP": 326862, "MPC70": 0, "trading_event": 174, "BMP": 8614}, {"SMP": 169233, "RenCas": 11908, "Butter": 55850, "QuantitySold": "27735", "Ched": 26883, "LAC": 9127, "SWP": 0, "AMF": 81673, "TwelveMonthQtySold": "707104", "date": "2016-11-01", "WMP": 343301, "MPC70": 0, "trading_event": 175, "BMP": 9129}, {"SMP": 168296, "RenCas": 11901, "Butter": 55540, "QuantitySold": "23902", "Ched": 26888, "LAC": 9379, "SWP": 0, "AMF": 80872, "TwelveMonthQtySold": "698343", "date": "2016-11-15", "WMP": 336333, "MPC70": 0, "trading_event": 176, "BMP": 9134}, {"SMP": 160020, "RenCas": 11488, "Butter": 51429, "QuantitySold": "22472", "Ched": 25315, "LAC": 9293, "SWP": 0, "AMF": 76843, "TwelveMonthQtySold": "662322", "date": "2016-12-06", "WMP": 319077, "MPC70": 0, "trading_event": 177, "BMP": 8857}, {"SMP": 159620, "RenCas": 11499, "Butter": 50145, "QuantitySold": "22321", "Ched": 25217, "LAC": 9507, "SWP": 0, "AMF": 76262, "TwelveMonthQtySold": "661358", "date": "2016-12-20", "WMP": 320422, "MPC70": 0, "trading_event": 178, "BMP": 8686}, {"SMP": 167703, "RenCas": 12093, "Butter": 51935, "QuantitySold": "22396", "Ched": 26722, "LAC": 9999, "SWP": 0, "AMF": 78909, "TwelveMonthQtySold": "695295", "date": "2017-01-03", "WMP": 338781, "MPC70": 0, "trading_event": 179, "BMP": 9153}, {"SMP": 165058, "RenCas": 12087, "Butter": 50662, "QuantitySold": "22030", "Ched": 26600, "LAC": 10199, "SWP": 0, "AMF": 78094, "TwelveMonthQtySold": "691577", "date": "2017-01-17", "WMP": 339893, "MPC70": 0, "trading_event": 180, "BMP": 8984}, {"SMP": 153924, "RenCas": 11539, "Butter": 47331, "QuantitySold": "21273", "Ched": 25098, "LAC": 10093, "SWP": 0, "AMF": 73966, "TwelveMonthQtySold": "650796", "date": "2017-02-07", "WMP": 320074, "MPC70": 0, "trading_event": 181, "BMP": 8771}, {"SMP": 152355, "RenCas": 11493, "Butter": 46743, "QuantitySold": "20479", "Ched": 24907, "LAC": 10298, "SWP": 0, "AMF": 73591, "TwelveMonthQtySold": "644654", "date": "2017-02-21", "WMP": 316648, "MPC70": 0, "trading_event": 182, "BMP": 8619}, {"SMP": 151458, "RenCas": 11371, "Butter": 46271, "QuantitySold": "22328", "Ched": 24649, "LAC": 10498, "SWP": 0, "AMF": 73787, "TwelveMonthQtySold": "638968", "date": "2017-03-07", "WMP": 312199, "MPC70": 0, "trading_event": 183, "BMP": 8735}, {"SMP": 149961, "RenCas": 11307, "Butter": 46008, "QuantitySold": "22498", "Ched": 24444, "LAC": 10698, "SWP": 0, "AMF": 73762, "TwelveMonthQtySold": "636401", "date": "2017-03-21", "WMP": 311695, "MPC70": 0, "trading_event": 184, "BMP": 8526}, {"SMP": 153885, "RenCas": 11815, "Butter": 47436, "QuantitySold": "22642", "Ched": 25489, "LAC": 11198, "SWP": 0, "AMF": 75759, "TwelveMonthQtySold": "658797", "date": "2017-04-04", "WMP": 324396, "MPC70": 0, "trading_event": 185, "BMP": 8819}, {"SMP": 151852, "RenCas": 11475, "Butter": 46900, "QuantitySold": "22927", "Ched": 25340, "LAC": 11400, "SWP": 0, "AMF": 75689, "TwelveMonthQtySold": "655156", "date": "2017-04-18", "WMP": 323765, "MPC70": 0, "trading_event": 186, "BMP": 8735}, {"SMP": 146798, "RenCas": 10780, "Butter": 45449, "QuantitySold": "22633", "Ched": 24225, "LAC": 11100, "SWP": 0, "AMF": 73133, "TwelveMonthQtySold": "633226", "date": "2017-05-02", "WMP": 313161, "MPC70": 0, "trading_event": 187, "BMP": 8580}, {"SMP": 145776, "RenCas": 10435, "Butter": 45392, "QuantitySold": "21236", "Ched": 24077, "LAC": 11108, "SWP": 0, "AMF": 71993, "TwelveMonthQtySold": "630025", "date": "2017-05-16", "WMP": 312511, "MPC70": 0, "trading_event": 188, "BMP": 8733}, {"SMP": 143996, "RenCas": 10080, "Butter": 44785, "QuantitySold": "22004", "Ched": 23763, "LAC": 11204, "SWP": 0, "AMF": 69173, "TwelveMonthQtySold": "628931", "date": "2017-06-06", "WMP": 316916, "MPC70": 0, "trading_event": 189, "BMP": 9014}, {"SMP": 143669, "RenCas": 10067, "Butter": 44014, "QuantitySold": "21171", "Ched": 23565, "LAC": 11309, "SWP": 0, "AMF": 67997, "TwelveMonthQtySold": "631023", "date": "2017-06-20", "WMP": 321647, "MPC70": 0, "trading_event": 190, "BMP": 0}, {"SMP": 150076, "RenCas": 10501, "Butter": 45263, "QuantitySold": "28574", "Ched": 24100, "LAC": 11709, "SWP": 0, "AMF": 69792, "TwelveMonthQtySold": "653665", "date": "2017-07-04", "WMP": 332910, "MPC70": 0, "trading_event": 191, "BMP": 9314}, {"SMP": 151483, "RenCas": 10597, "Butter": 44895, "QuantitySold": "26688", "Ched": 24011, "LAC": 11609, "SWP": 0, "AMF": 68329, "TwelveMonthQtySold": "653910", "date": "2017-07-18", "WMP": 333975, "MPC70": 0, "trading_event": 192, "BMP": 0}, {"SMP": 153797, "RenCas": 10737, "Butter": 44513, "QuantitySold": "32768", "Ched": 23854, "LAC": 11515, "SWP": 0, "AMF": 67203, "TwelveMonthQtySold": "655337", "date": "2017-08-01", "WMP": 334239, "MPC70": 0, "trading_event": 193, "BMP": 9479}, {"SMP": 154442, "RenCas": 10868, "Butter": 43800, "QuantitySold": "32260", "Ched": 24050, "LAC": 11403, "SWP": 0, "AMF": 66016, "TwelveMonthQtySold": "655958", "date": "2017-08-15", "WMP": 336375, "MPC70": 0, "trading_event": 194, "BMP": 0}, {"SMP": 147183, "RenCas": 10934, "Butter": 41051, "QuantitySold": "33501", "Ched": 23961, "LAC": 10803, "SWP": 0, "AMF": 61518, "TwelveMonthQtySold": "635803", "date": "2017-09-05", "WMP": 331310, "MPC70": 0, "trading_event": 195, "BMP": 9043}, {"SMP": 146095, "RenCas": 11176, "Butter": 40038, "QuantitySold": "34117", "Ched": 24361, "LAC": 10722, "SWP": 0, "AMF": 60485, "TwelveMonthQtySold": "633885", "date": "2017-09-19", "WMP": 332311, "MPC70": 0, "trading_event": 196, "BMP": 0}, {"SMP": 153512, "RenCas": 11621, "Butter": 41944, "QuantitySold": "37990", "Ched": 25461, "LAC": 11122, "SWP": 0, "AMF": 62521, "TwelveMonthQtySold": "662459", "date": "2017-10-03", "WMP": 346816, "MPC70": 0, "trading_event": 197, "BMP": 9462}, {"SMP": 152296, "RenCas": 11723, "Butter": 40715, "QuantitySold": "35669", "Ched": 25537, "LAC": 11022, "SWP": 0, "AMF": 60608, "TwelveMonthQtySold": "656647", "date": "2017-10-17", "WMP": 345765, "MPC70": 0, "trading_event": 198, "BMP": 0}, {"SMP": 143919, "RenCas": 11533, "Butter": 38197, "QuantitySold": "35072", "Ched": 24399, "LAC": 10340, "SWP": 0, "AMF": 55196, "TwelveMonthQtySold": "623139", "date": "2017-11-07", "WMP": 330770, "MPC70": 0, "trading_event": 199, "BMP": 8785}, {"SMP": 143696, "RenCas": 11670, "Butter": 37907, "QuantitySold": "35042", "Ched": 24299, "LAC": 10140, "SWP": 0, "AMF": 54417, "TwelveMonthQtySold": "617633", "date": "2017-11-21", "WMP": 327129, "MPC70": 0, "trading_event": 200, "BMP": 0}, {"SMP": 152769, "RenCas": 12169, "Butter": 40565, "QuantitySold": "29514", "Ched": 25597, "LAC": 10538, "SWP": 0, "AMF": 57059, "TwelveMonthQtySold": "651134", "date": "2017-12-05", "WMP": 343274, "MPC70": 0, "trading_event": 201, "BMP": 9163}, {"SMP": 151695, "RenCas": 12208, "Butter": 41318, "QuantitySold": "29592", "Ched": 25797, "LAC": 10434, "SWP": 0, "AMF": 55981, "TwelveMonthQtySold": "648503", "date": "2017-12-19", "WMP": 342450, "MPC70": 0, "trading_event": 202, "BMP": 0}, {"SMP": 152147, "RenCas": 12195, "Butter": 42059, "QuantitySold": "25400", "Ched": 25957, "LAC": 10292, "SWP": 0, "AMF": 54840, "TwelveMonthQtySold": "651407", "date": "2018-01-02", "WMP": 344837, "MPC70": 0, "trading_event": 203, "BMP": 9080}, {"SMP": 152382, "RenCas": 12176, "Butter": 42402, "QuantitySold": "23319", "Ched": 25877, "LAC": 10059, "SWP": 0, "AMF": 54210, "TwelveMonthQtySold": "653139", "date": "2018-01-16", "WMP": 347420, "MPC70": 0, "trading_event": 204, "BMP": 0}, {"SMP": 147619, "RenCas": 11476, "Butter": 40458, "QuantitySold": "22197", "Ched": 24348, "LAC": 9454, "SWP": 0, "AMF": 51342, "TwelveMonthQtySold": "628951", "date": "2018-02-06", "WMP": 335657, "MPC70": 0, "trading_event": 205, "BMP": 8597}, {"SMP": 151269, "RenCas": 11425, "Butter": 40665, "QuantitySold": "20256", "Ched": 24492, "LAC": 9163, "SWP": 0, "AMF": 51106, "TwelveMonthQtySold": "640091", "date": "2018-02-20", "WMP": 343622, "MPC70": 0, "trading_event": 206, "BMP": 0}, {"SMP": 158336, "RenCas": 11936, "Butter": 42310, "QuantitySold": "19292", "Ched": 25738, "LAC": 9397, "SWP": 0, "AMF": 53557, "TwelveMonthQtySold": "669605", "date": "2018-03-06", "WMP": 359504, "MPC70": 0, "trading_event": 207, "BMP": 8827}, {"SMP": 160231, "RenCas": 11915, "Butter": 43171, "QuantitySold": "18635", "Ched": 25963, "LAC": 9043, "SWP": 0, "AMF": 53092, "TwelveMonthQtySold": "676725", "date": "2018-03-20", "WMP": 364846, "MPC70": 0, "trading_event": 208, "BMP": 0}, {"SMP": 161865, "RenCas": 11702, "Butter": 43390, "QuantitySold": "17222", "Ched": 26023, "LAC": 8728, "SWP": 0, "AMF": 53404, "TwelveMonthQtySold": "679804", "date": "2018-04-03", "WMP": 365946, "MPC70": 0, "trading_event": 209, "BMP": 8746}, {"SMP": 163203, "RenCas": 11547, "Butter": 43558, "QuantitySold": "19262", "Ched": 26049, "LAC": 8636, "SWP": 0, "AMF": 54140, "TwelveMonthQtySold": "680727", "date": "2018-04-17", "WMP": 365141, "MPC70": 0, "trading_event": 210, "BMP": 0}, {"SMP": 159748, "RenCas": 11059, "Butter": 42638, "QuantitySold": "19508", "Ched": 24989, "LAC": 8136, "SWP": 0, "AMF": 51673, "TwelveMonthQtySold": "658697", "date": "2018-05-01", "WMP": 352183, "MPC70": 0, "trading_event": 211, "BMP": 8271}, {"SMP": 160947, "RenCas": 11001, "Butter": 43101, "QuantitySold": "18161", "Ched": 25104, "LAC": 8036, "SWP": 0, "AMF": 52472, "TwelveMonthQtySold": "659621", "date": "2018-05-15", "WMP": 350526, "MPC70": 0, "trading_event": 212, "BMP": 0}, {"SMP": 166812, "RenCas": 11139, "Butter": 44871, "QuantitySold": "21580", "Ched": 26178, "LAC": 7996, "SWP": 0, "AMF": 56317, "TwelveMonthQtySold": "678690", "date": "2018-06-05", "WMP": 356539, "MPC70": 0, "trading_event": 213, "BMP": 8838}, {"SMP": 166672, "RenCas": 10973, "Butter": 45291, "QuantitySold": "21634", "Ched": 26248, "LAC": 7914, "SWP": 0, "AMF": 57640, "TwelveMonthQtySold": "674997", "date": "2018-06-19", "WMP": 352055, "MPC70": 0, "trading_event": 214, "BMP": 0}, {"SMP": 166563, "RenCas": 10847, "Butter": 45514, "QuantitySold": "26519", "Ched": 26076, "LAC": 0, "SWP": 0, "AMF": 58289, "TwelveMonthQtySold": "669721", "date": "2018-07-03", "WMP": 345890, "MPC70": 0, "trading_event": 215, "BMP": 8735}, {"SMP": 164111, "RenCas": 10693, "Butter": 45492, "QuantitySold": "25454", "Ched": 26042, "LAC": 7672, "SWP": 0, "AMF": 59152, "TwelveMonthQtySold": "666341", "date": "2018-07-17", "WMP": 345003, "MPC70": 0, "trading_event": 216, "BMP": 8176}, {"SMP": 153144, "RenCas": 10279, "Butter": 43539, "QuantitySold": "34076", "Ched": 25493, "LAC": 7167, "SWP": 0, "AMF": 57765, "TwelveMonthQtySold": "640289", "date": "2018-08-07", "WMP": 334887, "MPC70": 0, "trading_event": 217, "BMP": 8015}, {"SMP": 149323, "RenCas": 10279, "Butter": 43485, "QuantitySold": "32041", "Ched": 25411, "LAC": 6979, "SWP": 0, "AMF": 58325, "TwelveMonthQtySold": "637214", "date": "2018-08-21", "WMP": 335421, "MPC70": 0, "trading_event": 218, "BMP": 0}, {"SMP": 153832, "RenCas": 10657, "Butter": 44809, "QuantitySold": "38811", "Ched": 26226, "LAC": 7329, "SWP": 0, "AMF": 60865, "TwelveMonthQtySold": "658794", "date": "2018-09-04", "WMP": 346635, "MPC70": 0, "trading_event": 219, "BMP": 8391}, {"SMP": 153253, "RenCas": 10612, "Butter": 44912, "QuantitySold": "39143", "Ched": 26399, "LAC": 7113, "SWP": 0, "AMF": 61576, "TwelveMonthQtySold": "658424", "date": "2018-09-18", "WMP": 346836, "MPC70": 0, "trading_event": 220, "BMP": 0}, {"SMP": 154598, "RenCas": 10764, "Butter": 45551, "QuantitySold": "41981", "Ched": 26613, "LAC": 6713, "SWP": 0, "AMF": 62277, "TwelveMonthQtySold": "663772", "date": "2018-10-02", "WMP": 349035, "MPC70": 0, "trading_event": 221, "BMP": 8171}, {"SMP": 153366, "RenCas": 10814, "Butter": 45704, "QuantitySold": "41945", "Ched": 26622, "LAC": 6413, "SWP": 0, "AMF": 62889, "TwelveMonthQtySold": "660652", "date": "2018-10-16", "WMP": 347288, "MPC70": 0, "trading_event": 222, "BMP": 0}, {"SMP": 147344, "RenCas": 10287, "Butter": 43825, "QuantitySold": "42412", "Ched": 25637, "LAC": 5813, "SWP": 0, "AMF": 61296, "TwelveMonthQtySold": "635272", "date": "2018-11-06", "WMP": 333463, "MPC70": 0, "trading_event": 223, "BMP": 7557}, {"SMP": 147339, "RenCas": 10262, "Butter": 44233, "QuantitySold": "42966", "Ched": 25713, "LAC": 5701, "SWP": 50, "AMF": 61669, "TwelveMonthQtySold": "635053", "date": "2018-11-20", "WMP": 332529, "MPC70": 0, "trading_event": 224, "BMP": 0}, {"SMP": 156513, "RenCas": 10709, "Butter": 47094, "QuantitySold": "36450", "Ched": 27143, "LAC": 5894, "SWP": 0, "AMF": 64812, "TwelveMonthQtySold": "673864", "date": "2018-12-04", "WMP": 353335, "MPC70": 0, "trading_event": 225, "BMP": 8314}, {"SMP": 156804, "RenCas": 10632, "Butter": 47180, "QuantitySold": "36181", "Ched": 27290, "LAC": 5714, "SWP": 0, "AMF": 65318, "TwelveMonthQtySold": "679506", "date": "2018-12-18", "WMP": 358992, "MPC70": 0, "trading_event": 226, "BMP": 0}, {"SMP": 156559, "RenCas": 10504, "Butter": 47237, "QuantitySold": "28651", "Ched": 27119, "LAC": 5518, "SWP": 0, "AMF": 66253, "TwelveMonthQtySold": "687370", "date": "2019-01-02", "WMP": 365758, "MPC70": 0, "trading_event": 227, "BMP": 8372}, {"SMP": 156452, "RenCas": 10403, "Butter": 47560, "QuantitySold": "27909", "Ched": 26918, "LAC": 5358, "SWP": 0, "AMF": 67528, "TwelveMonthQtySold": "691325", "date": "2019-01-15", "WMP": 369498, "MPC70": 0, "trading_event": 228, "BMP": 0}, {"SMP": 156437, "RenCas": 10326, "Butter": 48050, "QuantitySold": "23326", "Ched": 26779, "LAC": 5299, "SWP": 0, "AMF": 69017, "TwelveMonthQtySold": "698068", "date": "2019-02-06", "WMP": 373825, "MPC70": 0, "trading_event": 229, "BMP": 8285}, {"SMP": 157092, "RenCas": 10257, "Butter": 49606, "QuantitySold": "25324", "Ched": 26784, "LAC": 5095, "SWP": 0, "AMF": 69573, "TwelveMonthQtySold": "705962", "date": "2019-02-19", "WMP": 379903, "MPC70": 0, "trading_event": 230, "BMP": 0}, {"SMP": 155606, "RenCas": 10139, "Butter": 50418, "QuantitySold": "23930", "Ched": 26848, "LAC": 5137, "SWP": 0, "AMF": 70220, "TwelveMonthQtySold": "707370", "date": "2019-03-05", "WMP": 380839, "MPC70": 0, "trading_event": 231, "BMP": 8098}, {"SMP": 155688, "RenCas": 10089, "Butter": 51193, "QuantitySold": "21713", "Ched": 26628, "LAC": 5153, "SWP": 0, "AMF": 70581, "TwelveMonthQtySold": "714037", "date": "2019-03-19", "WMP": 387020, "MPC70": 0, "trading_event": 232, "BMP": 0}, {"SMP": 148539, "RenCas": 9591, "Butter": 49262, "QuantitySold": "17854", "Ched": 25364, "LAC": 5007, "SWP": 0, "AMF": 68116, "TwelveMonthQtySold": "684445", "date": "2019-04-02", "WMP": 370881, "MPC70": 0, "trading_event": 233, "BMP": 7620}, {"SMP": 153256, "RenCas": 10040, "Butter": 51876, "QuantitySold": "16166", "Ched": 26379, "LAC": 5202, "SWP": 0, "AMF": 69968, "TwelveMonthQtySold": "715605", "date": "2019-04-16", "WMP": 391139, "MPC70": 0, "trading_event": 234, "BMP": 0}, {"SMP": 147994, "RenCas": 9687, "Butter": 50280, "QuantitySold": "15375", "Ched": 25308, "LAC": 4794, "SWP": 0, "AMF": 67235, "TwelveMonthQtySold": "692286", "date": "2019-05-07", "WMP": 379243, "MPC70": 0, "trading_event": 235, "BMP": 7680}, {"SMP": 152859, "RenCas": 10095, "Butter": 50731, "QuantitySold": "15510", "Ched": 26113, "LAC": 4988, "SWP": 0, "AMF": 68734, "TwelveMonthQtySold": "718739", "date": "2019-05-21", "WMP": 397398, "MPC70": 0, "trading_event": 236, "BMP": 0}, {"SMP": 155459, "RenCas": 10030, "Butter": 49940, "QuantitySold": "19874", "Ched": 25611, "LAC": 5088, "SWP": 0, "AMF": 68126, "TwelveMonthQtySold": "722413", "date": "2019-06-04", "WMP": 399639, "MPC70": 0, "trading_event": 237, "BMP": 8455}, {"SMP": 158092, "RenCas": 9928, "Butter": 49376, "QuantitySold": "24239", "Ched": 25103, "LAC": 5128, "SWP": 0, "AMF": 67114, "TwelveMonthQtySold": "724834", "date": "2019-06-18", "WMP": 402237, "MPC70": 0, "trading_event": 238, "BMP": 0}, {"SMP": 158616, "RenCas": 9854, "Butter": 48471, "QuantitySold": "24711", "Ched": 24501, "LAC": 5028, "SWP": 0, "AMF": 66001, "TwelveMonthQtySold": "724053", "date": "2019-07-02", "WMP": 402983, "MPC70": 0, "trading_event": 239, "BMP": 8534}, {"SMP": 158648, "RenCas": 9756, "Butter": 47964, "QuantitySold": "25000", "Ched": 24299, "LAC": 4928, "SWP": 0, "AMF": 64699, "TwelveMonthQtySold": "722997", "date": "2019-07-16", "WMP": 404710, "MPC70": 0, "trading_event": 240, "BMP": 0}, {"SMP": 154286, "RenCas": 9344, "Butter": 46357, "QuantitySold": "34969", "Ched": 23613, "LAC": 4568, "SWP": 0, "AMF": 60872, "TwelveMonthQtySold": "699602", "date": "2019-08-06", "WMP": 392481, "MPC70": 0, "trading_event": 241, "BMP": 8016}, {"SMP": 154853, "RenCas": 9231, "Butter": 45930, "QuantitySold": "34410", "Ched": 23418, "LAC": 4568, "SWP": 0, "AMF": 59646, "TwelveMonthQtySold": "696951", "date": "2019-08-20", "WMP": 391274, "MPC70": 0, "trading_event": 242, "BMP": 0}, {"SMP": 159748, "RenCas": 9598, "Butter": 47075, "QuantitySold": "39689", "Ched": 24168, "LAC": 4748, "SWP": 0, "AMF": 61823, "TwelveMonthQtySold": "716825", "date": "2019-09-03", "WMP": 401028, "MPC70": 0, "trading_event": 243, "BMP": 8622}, {"SMP": 162601, "RenCas": 9583, "Butter": 47024, "QuantitySold": "37345", "Ched": 24087, "LAC": 4598, "SWP": 0, "AMF": 61972, "TwelveMonthQtySold": "719484", "date": "2019-09-17", "WMP": 401432, "MPC70": 0, "trading_event": 244, "BMP": 0}, {"SMP": 163480, "RenCas": 9825, "Butter": 46901, "QuantitySold": "38716", "Ched": 24316, "LAC": 4614, "SWP": 0, "AMF": 62083, "TwelveMonthQtySold": "722561", "date": "2019-10-01", "WMP": 402380, "MPC70": 0, "trading_event": 245, "BMP": 8947}, {"SMP": 163610, "RenCas": 9940, "Butter": 46262, "QuantitySold": "38712", "Ched": 24206, "LAC": 4798, "SWP": 0, "AMF": 62230, "TwelveMonthQtySold": "721042", "date": "2019-10-15", "WMP": 401532, "MPC70": 0, "trading_event": 246, "BMP": 0}, {"SMP": 165966, "RenCas": 10025, "Butter": 46408, "QuantitySold": "38681", "Ched": 24391, "LAC": 4878, "SWP": 0, "AMF": 62948, "TwelveMonthQtySold": "730557", "date": "2019-11-05", "WMP": 406738, "MPC70": 0, "trading_event": 247, "BMP": 9188}, {"SMP": 165938, "RenCas": 10183, "Butter": 46508, "QuantitySold": "37968", "Ched": 24238, "LAC": 4978, "SWP": 0, "AMF": 62928, "TwelveMonthQtySold": "730891", "date": "2019-11-19", "WMP": 407615, "MPC70": 0, "trading_event": 248, "BMP": 0}, {"SMP": 167252, "RenCas": 10237, "Butter": 46607, "QuantitySold": "36258", "Ched": 24147, "LAC": 4975, "SWP": 0, "AMF": 63048, "TwelveMonthQtySold": "738539", "date": "2019-12-03", "WMP": 412977, "MPC70": 0, "trading_event": 249, "BMP": 9281}, {"SMP": 166882, "RenCas": 10327, "Butter": 46584, "QuantitySold": "35748", "Ched": 24094, "LAC": 4982, "SWP": 0, "AMF": 62970, "TwelveMonthQtySold": "737073", "date": "2019-12-17", "WMP": 412695, "MPC70": 0, "trading_event": 250, "BMP": 0}, {"SMP": 157764, "RenCas": 9936, "Butter": 44078, "QuantitySold": "33050", "Ched": 22630, "LAC": 4750, "SWP": 0, "AMF": 59648, "TwelveMonthQtySold": "694665", "date": "2020-01-07", "WMP": 387502, "MPC70": 0, "trading_event": 251, "BMP": 8342}, {"SMP": 157484, "RenCas": 9961, "Butter": 44079, "QuantitySold": "33165", "Ched": 22653, "LAC": 4752, "SWP": 0, "AMF": 59674, "TwelveMonthQtySold": "691432", "date": "2020-01-21", "WMP": 384472, "MPC70": 0, "trading_event": 252, "BMP": 0}, {"SMP": 166000, "RenCas": 10295, "Butter": 46154, "QuantitySold": "29006", "Ched": 23934, "LAC": 4952, "SWP": 0, "AMF": 63535, "TwelveMonthQtySold": "730113", "date": "2020-02-04", "WMP": 406144, "MPC70": 0, "trading_event": 253, "BMP": 9084}, {"SMP": 166653, "RenCas": 10054, "Butter": 46070, "QuantitySold": "28181", "Ched": 23747, "LAC": 4952, "SWP": 0, "AMF": 63532, "TwelveMonthQtySold": "725669", "date": "2020-02-18", "WMP": 402289, "MPC70": 0, "trading_event": 254, "BMP": 0}, {"SMP": 165916, "RenCas": 9789, "Butter": 45919, "QuantitySold": "25576", "Ched": 23363, "LAC": 4967, "SWP": 0, "AMF": 63561, "TwelveMonthQtySold": "718961", "date": "2020-03-03", "WMP": 396378, "MPC70": 0, "trading_event": 255, "BMP": 9068}, {"SMP": 166684, "RenCas": 9571, "Butter": 46003, "QuantitySold": "24209", "Ched": 22966, "LAC": 4919, "SWP": 0, "AMF": 63731, "TwelveMonthQtySold": "718259", "date": "2020-03-17", "WMP": 395828, "MPC70": 0, "trading_event": 256, "BMP": 0}, {"SMP": 161580, "RenCas": 8882, "Butter": 44343, "QuantitySold": "20302", "Ched": 21585, "LAC": 4672, "SWP": 0, "AMF": 61045, "TwelveMonthQtySold": "686477", "date": "2020-04-07", "WMP": 375599, "MPC70": 0, "trading_event": 257, "BMP": 8771}, {"SMP": 163983, "RenCas": 8617, "Butter": 44314, "QuantitySold": "20601", "Ched": 21252, "LAC": 4689, "SWP": 0, "AMF": 62115, "TwelveMonthQtySold": "691733", "date": "2020-04-21", "WMP": 377992, "MPC70": 0, "trading_event": 258, "BMP": 0}, {"SMP": 170438, "RenCas": 8758, "Butter": 45510, "QuantitySold": "16442", "Ched": 21655, "LAC": 4887, "SWP": 0, "AMF": 64875, "TwelveMonthQtySold": "720739", "date": "2020-05-05", "WMP": 395146, "MPC70": 0, "trading_event": 259, "BMP": 9470}, {"SMP": 172050, "RenCas": 8539, "Butter": 45422, "QuantitySold": "16787", "Ched": 21130, "LAC": 4885, "SWP": 0, "AMF": 65846, "TwelveMonthQtySold": "725594", "date": "2020-05-19", "WMP": 398918, "MPC70": 0, "trading_event": 260, "BMP": 0}, {"SMP": 173238, "RenCas": 0, "Butter": 45158, "QuantitySold": "21968", "Ched": 20634, "LAC": 4885, "SWP": 0, "AMF": 66244, "TwelveMonthQtySold": "725846", "date": "2020-06-02", "WMP": 397773, "MPC70": 0, "trading_event": 261, "BMP": 9627}, {"SMP": 172676, "RenCas": 0, "Butter": 45206, "QuantitySold": "21410", "Ched": 20390, "LAC": 4877, "SWP": 0, "AMF": 66604, "TwelveMonthQtySold": "726125", "date": "2020-06-16", "WMP": 399318, "MPC70": 0, "trading_event": 262, "BMP": 0}, {"SMP": 166658, "RenCas": 0, "Butter": 44183, "QuantitySold": "25688", "Ched": 20105, "LAC": 4677, "SWP": 0, "AMF": 64859, "TwelveMonthQtySold": "706860", "date": "2020-07-07", "WMP": 389747, "MPC70": 0, "trading_event": 263, "BMP": 8795}, {"SMP": 167595, "RenCas": 0, "Butter": 44153, "QuantitySold": "23995", "Ched": 20177, "LAC": 4684, "SWP": 0, "AMF": 65490, "TwelveMonthQtySold": "711295", "date": "2020-07-21", "WMP": 392703, "MPC70": 0, "trading_event": 264, "BMP": 0}, {"SMP": 171242, "RenCas": 0, "Butter": 44853, "QuantitySold": "32696", "Ched": 20461, "LAC": 4884, "SWP": 0, "AMF": 67111, "TwelveMonthQtySold": "727737", "date": "2020-08-04", "WMP": 401736, "MPC70": 0, "trading_event": 265, "BMP": 9608}, {"SMP": 171545, "RenCas": 0, "Butter": 44867, "QuantitySold": "31331", "Ched": 20560, "LAC": 4884, "SWP": 0, "AMF": 67458, "TwelveMonthQtySold": "729149", "date": "2020-08-18", "WMP": 403271, "MPC70": 0, "trading_event": 266, "BMP": 0}, {"SMP": 172127, "RenCas": 0, "Butter": 45633, "QuantitySold": "35656", "Ched": 21247, "LAC": 4866, "SWP": 0, "AMF": 68457, "TwelveMonthQtySold": "735607", "date": "2020-09-01", "WMP": 406225, "MPC70": 0, "trading_event": 267, "BMP": 9538}, {"SMP": 171829, "RenCas": 0, "Butter": 46116, "QuantitySold": "33791", "Ched": 21386, "LAC": 4885, "SWP": 0, "AMF": 68483, "TwelveMonthQtySold": "737143", "date": "2020-09-15", "WMP": 408365, "MPC70": 0, "trading_event": 268, "BMP": 0}, {"SMP": 164638, "RenCas": 0, "Butter": 45771, "QuantitySold": "35090", "Ched": 20803, "LAC": 4685, "SWP": 0, "AMF": 65529, "TwelveMonthQtySold": "713881", "date": "2020-10-06", "WMP": 397307, "MPC70": 0, "trading_event": 269, "BMP": 8962}, {"SMP": 163867, "RenCas": 0, "Butter": 46817, "QuantitySold": "34648", "Ched": 20947, "LAC": 4701, "SWP": 0, "AMF": 65193, "TwelveMonthQtySold": "712876", "date": "2020-10-20", "WMP": 396835, "MPC70": 0, "trading_event": 270, "BMP": 0}, {"SMP": 170489, "RenCas": 0, "Butter": 50155, "QuantitySold": "35418", "Ched": 22263, "LAC": 4884, "SWP": 0, "AMF": 68012, "TwelveMonthQtySold": "745572", "date": "2020-11-03", "WMP": 414448, "MPC70": 0, "trading_event": 271, "BMP": 9767}, {"SMP": 168719, "RenCas": 0, "Butter": 50538, "QuantitySold": "35303", "Ched": 22326, "LAC": 4904, "SWP": 0, "AMF": 67700, "TwelveMonthQtySold": "741934", "date": "2020-11-17", "WMP": 413845, "MPC70": 0, "trading_event": 272, "BMP": 0}, {"SMP": 167220, "RenCas": 0, "Butter": 51324, "QuantitySold": "32062", "Ched": 22277, "LAC": 4904, "SWP": 0, "AMF": 67411, "TwelveMonthQtySold": "743180", "date": "2020-12-01", "WMP": 415925, "MPC70": 0, "trading_event": 273, "BMP": 9727}, {"SMP": 163917, "RenCas": 0, "Butter": 51691, "QuantitySold": "31701", "Ched": 22228, "LAC": 4919, "SWP": 0, "AMF": 67264, "TwelveMonthQtySold": "737282", "date": "2020-12-15", "WMP": 414467, "MPC70": 0, "trading_event": 274, "BMP": 0}, {"SMP": 152464, "RenCas": 0, "Butter": 47998, "QuantitySold": "30313", "Ched": 20720, "LAC": 4727, "SWP": 0, "AMF": 64215, "TwelveMonthQtySold": "696311", "date": "2021-01-05", "WMP": 394230, "MPC70": 0, "trading_event": 275, "BMP": 9098}, {"SMP": 149987, "RenCas": 0, "Butter": 47244, "QuantitySold": "29606", "Ched": 20578, "LAC": 4707, "SWP": 0, "AMF": 64130, "TwelveMonthQtySold": "692247", "date": "2021-01-19", "WMP": 394099, "MPC70": 0, "trading_event": 276, "BMP": 0}, {"SMP": 156449, "RenCas": 0, "Butter": 49500, "QuantitySold": "28707", "Ched": 21738, "LAC": 4907, "SWP": 0, "AMF": 67153, "TwelveMonthQtySold": "727665", "date": "2021-02-02", "WMP": 415632, "MPC70": 0, "trading_event": 277, "BMP": 9882}, {"SMP": 154067, "RenCas": 0, "Butter": 49671, "QuantitySold": "26883", "Ched": 21635, "LAC": 4906, "SWP": 0, "AMF": 66428, "TwelveMonthQtySold": "724287", "date": "2021-02-16", "WMP": 416370, "MPC70": 0, "trading_event": 278, "BMP": 0}, {"SMP": 150922, "RenCas": 0, "Butter": 49104, "QuantitySold": "25554", "Ched": 21348, "LAC": 4904, "SWP": 0, "AMF": 65586, "TwelveMonthQtySold": "718381", "date": "2021-03-02", "WMP": 414919, "MPC70": 0, "trading_event": 279, "BMP": 9785}, {"SMP": 149507, "RenCas": 0, "Butter": 47944, "QuantitySold": "26872", "Ched": 21131, "LAC": 4904, "SWP": 0, "AMF": 65338, "TwelveMonthQtySold": "713824", "date": "2021-03-16", "WMP": 414325, "MPC70": 0, "trading_event": 280, "BMP": 0}, {"SMP": 147436, "RenCas": 0, "Butter": 47544, "QuantitySold": "25104", "Ched": 20738, "LAC": 4884, "SWP": 0, "AMF": 64183, "TwelveMonthQtySold": "708389", "date": "2021-04-06", "WMP": 412396, "MPC70": 0, "trading_event": 281, "BMP": 9812}, {"SMP": 146553, "RenCas": 0, "Butter": 46738, "QuantitySold": "25040", "Ched": 20502, "LAC": 4880, "SWP": 0, "AMF": 63772, "TwelveMonthQtySold": "704945", "date": "2021-04-20", "WMP": 412170, "MPC70": 0, "trading_event": 282, "BMP": 0}, {"SMP": 144684, "RenCas": 0, "Butter": 46184, "QuantitySold": "22020", "Ched": 20276, "LAC": 4865, "SWP": 0, "AMF": 62545, "TwelveMonthQtySold": "700487", "date": "2021-05-04", "WMP": 411012, "MPC70": 0, "trading_event": 283, "BMP": 9840}, {"SMP": 144275, "RenCas": 0, "Butter": 46514, "QuantitySold": "21140", "Ched": 20263, "LAC": 4867, "SWP": 0, "AMF": 61786, "TwelveMonthQtySold": "698364", "date": "2021-05-18", "WMP": 410578, "MPC70": 0, "trading_event": 284, "BMP": 0}, {"SMP": 144645, "RenCas": 0, "Butter": 46557, "QuantitySold": "22825", "Ched": 20203, "LAC": 4872, "SWP": 0, "AMF": 60870, "TwelveMonthQtySold": "695737", "date": "2021-06-01", "WMP": 407894, "MPC70": 0, "trading_event": 285, "BMP": 9917}, {"SMP": 144670, "RenCas": 0, "Butter": 46819, "QuantitySold": "21522", "Ched": 19859, "LAC": 4853, "SWP": 0, "AMF": 59915, "TwelveMonthQtySold": "697033", "date": "2021-06-15", "WMP": 411178, "MPC70": 0, "trading_event": 286, "BMP": 0}, {"SMP": 144331, "RenCas": 0, "Butter": 46812, "QuantitySold": "24278", "Ched": 19640, "LAC": 4861, "SWP": 0, "AMF": 58987, "TwelveMonthQtySold": "697928", "date": "2021-07-06", "WMP": 412867, "MPC70": 0, "trading_event": 287, "BMP": 9888}, {"SMP": 145192, "RenCas": 0, "Butter": 47464, "QuantitySold": "22405", "Ched": 19413, "LAC": 4879, "SWP": 0, "AMF": 58669, "TwelveMonthQtySold": "702666", "date": "2021-07-20", "WMP": 417340, "MPC70": 0, "trading_event": 288, "BMP": 0}, {"SMP": 144719, "RenCas": 0, "Butter": 48204, "QuantitySold": "24084", "Ched": 19253, "LAC": 4892, "SWP": 0, "AMF": 58699, "TwelveMonthQtySold": "704085", "date": "2021-08-03", "WMP": 417923, "MPC70": 0, "trading_event": 289, "BMP": 10083}, {"SMP": 145659, "RenCas": 0, "Butter": 49025, "QuantitySold": "22543", "Ched": 19188, "LAC": 4892, "SWP": 0, "AMF": 58940, "TwelveMonthQtySold": "708783", "date": "2021-08-17", "WMP": 421641, "MPC70": 0, "trading_event": 290, "BMP": 0}, {"SMP": 142482, "RenCas": 0, "Butter": 47930, "QuantitySold": "25093", "Ched": 18748, "LAC": 4694, "SWP": 0, "AMF": 57839, "TwelveMonthQtySold": "692853", "date": "2021-09-07", "WMP": 411810, "MPC70": 0, "trading_event": 291, "BMP": 9350}, {"SMP": 142613, "RenCas": 0, "Butter": 47510, "QuantitySold": "24476", "Ched": 18604, "LAC": 4695, "SWP": 0, "AMF": 58275, "TwelveMonthQtySold": "692965", "date": "2021-09-21", "WMP": 411918, "MPC70": 0, "trading_event": 292, "BMP": 0}, {"SMP": 147943, "RenCas": 0, "Butter": 49455, "QuantitySold": "28667", "Ched": 19676, "LAC": 5029, "SWP": 0, "AMF": 61196, "TwelveMonthQtySold": "717243", "date": "2021-10-05", "WMP": 424024, "MPC70": 0, "trading_event": 293, "BMP": 9920}, {"SMP": 147172, "RenCas": 0, "Butter": 48922, "QuantitySold": "27836", "Ched": 19261, "LAC": 5171, "SWP": 0, "AMF": 61740, "TwelveMonthQtySold": "713960", "date": "2021-10-19", "WMP": 422579, "MPC70": 0, "trading_event": 294, "BMP": 0}, {"SMP": 146293, "RenCas": 0, "Butter": 48393, "QuantitySold": "29915", "Ched": 19076, "LAC": 5271, "SWP": 0, "AMF": 62124, "TwelveMonthQtySold": "714049", "date": "2021-11-02", "WMP": 423042, "MPC70": 0, "trading_event": 295, "BMP": 9850}, {"SMP": 144149, "RenCas": 0, "Butter": 47201, "QuantitySold": "30397", "Ched": 18774, "LAC": 5342, "SWP": 0, "AMF": 61878, "TwelveMonthQtySold": "703896", "date": "2021-11-16", "WMP": 417507, "MPC70": 0, "trading_event": 296, "BMP": 0}, {"SMP": 135502, "RenCas": 0, "Butter": 43216, "QuantitySold": "31092", "Ched": 17226, "LAC": 5124, "SWP": 0, "AMF": 58608, "TwelveMonthQtySold": "662002", "date": "2021-12-07", "WMP": 393207, "MPC70": 0, "trading_event": 297, "BMP": 9119}, {"SMP": 134437, "RenCas": 0, "Butter": 42136, "QuantitySold": "30375", "Ched": 16968, "LAC": 5199, "SWP": 0, "AMF": 58425, "TwelveMonthQtySold": "652687", "date": "2021-12-21", "WMP": 386403, "MPC70": 0, "trading_event": 298, "BMP": 0}, {"SMP": 140650, "RenCas": 0, "Butter": 44451, "QuantitySold": "30685", "Ched": 18024, "LAC": 0, "SWP": 0, "AMF": 61367, "TwelveMonthQtySold": "681354", "date": "2022-01-04", "WMP": 401543, "MPC70": 0, "trading_event": 299, "BMP": 9884}, {"SMP": 140778, "RenCas": 0, "Butter": 44172, "QuantitySold": "30644", "Ched": 17780, "LAC": 0, "SWP": 0, "AMF": 61228, "TwelveMonthQtySold": "674100", "date": "2022-01-18", "WMP": 395653, "MPC70": 0, "trading_event": 300, "BMP": 0}]